metagent/__init__.py
metagent-0.1.0.dist-info/METADATA
metagent-0.1.0.dist-info/WHEEL
metagent-0.1.0.dist-info/RECORD
