Metadata-Version: 2.1
Name: metagent
Version: 0.1.0
Summary: 
Author: Bo Chen
Author-email: bochen0909@gmail.com
Requires-Python: >=3.11,<4.0
Classifier: Programming Language :: Python :: 3
Classifier: Programming Language :: Python :: 3.11
Classifier: Programming Language :: Python :: 3.12
Classifier: Programming Language :: Python :: 3.13
